README
setup.py
django_fossil.egg-info/PKG-INFO
django_fossil.egg-info/SOURCES.txt
django_fossil.egg-info/dependency_links.txt
django_fossil.egg-info/top_level.txt
fossil/__init__.py
fossil/fields.py
fossil/models.py
fossil/migrations/0001_initial.py
fossil/migrations/0002_most_recent_previous_revision.py
fossil/migrations/0003_index.py
fossil/migrations/0004_revision_sequential.py
fossil/migrations/0005_indexed_value_null.py
fossil/migrations/__init__.py