Metadata-Version: 1.0
Name: django-fossil
Version: 0.8-stable
Summary: Fossil is a library to store fossilized tracks of objects from Django's ORM
Home-page: http://reddes.bvsalud.org/projects/clinical-trials/browser/sandbox/django-fossil
Author: OpenTrials team (Marinho Brandao, Luciano Ramalho and Rafael Soares)
Author-email: opentrials-dev@listas.bireme.br
License: GNU Lesser General Public License (LGPL)
Platform: UNKNOWN
